[{"r":"Arica y Parinacota","pop":244569,"lic":73.3,"prox":7.1,"cond":197059,"a0":18,"a15":4,"a18":17,"a30":23,"a45":20,"a60":18},{"r":"Tarapacá","pop":369806,"lic":70.9,"prox":7.3,"cond":289568,"a0":19,"a15":4,"a18":18,"a30":24,"a45":20,"a60":15},{"r":"Antofagasta","pop":635416,"lic":73.2,"prox":7.1,"cond":509059,"a0":17,"a15":4,"a18":17,"a30":26,"a45":22,"a60":14},{"r":"Atacama","pop":299180,"lic":73.2,"prox":7.1,"cond":239813,"a0":18,"a15":4,"a18":17,"a30":24,"a45":21,"a60":16},{"r":"Coquimbo","pop":832864,"lic":74.6,"prox":6.9,"cond":676273,"a0":18,"a15":4,"a18":16,"a30":22,"a45":21,"a60":19},{"r":"Valparaíso","pop":1896053,"lic":76.8,"prox":6.4,"cond":1571564,"a0":16,"a15":4,"a18":16,"a30":22,"a45":21,"a60":21},{"r":"Metropolitana","pop":7400741,"lic":76.3,"prox":6.4,"cond":6099210,"a0":16,"a15":4,"a18":17,"a30":23,"a45":21,"a60":19},{"r":"O'Higgins","pop":987228,"lic":75.5,"prox":6.5,"cond":810347,"a0":18,"a15":4,"a18":16,"a30":22,"a45":21,"a60":19},{"r":"Maule","pop":1118520,"lic":74.5,"prox":6.8,"cond":905541,"a0":18,"a15":4,"a18":16,"a30":21,"a45":21,"a60":20},{"r":"Ñuble","pop":480609,"lic":72.6,"prox":7.2,"cond":384007,"a0":18,"a15":4,"a18":15,"a30":21,"a45":21,"a60":21},{"r":"Biobío","pop":1556805,"lic":75,"prox":6.8,"cond":1264273,"a0":17,"a15":4,"a18":16,"a30":22,"a45":21,"a60":20},{"r":"La Araucanía","pop":957224,"lic":71.2,"prox":7.5,"cond":748551,"a0":19,"a15":4,"a18":16,"a30":21,"a45":20,"a60":20},{"r":"Los Ríos","pop":384837,"lic":73.1,"prox":7,"cond":308197,"a0":17,"a15":4,"a18":15,"a30":22,"a45":22,"a60":20},{"r":"Los Lagos","pop":828708,"lic":72.8,"prox":7.2,"cond":664568,"a0":18,"a15":4,"a18":16,"a30":22,"a45":21,"a60":19},{"r":"Aysén","pop":103158,"lic":74.6,"prox":6.7,"cond":84068,"a0":17,"a15":4,"a18":17,"a30":25,"a45":23,"a60":14},{"r":"Magallanes","pop":164662,"lic":76.6,"prox":6.1,"cond":135527,"a0":15,"a15":4,"a18":17,"a30":25,"a45":22,"a60":17}]